solscan_mcp_server/__init__.py
solscan_mcp_server/__main__.py
solscan_mcp_server/api.py
solscan_mcp_server/server.py
mseep_solscan_mcp_server-0.2.1.dist-info/METADATA
mseep_solscan_mcp_server-0.2.1.dist-info/WHEEL
mseep_solscan_mcp_server-0.2.1.dist-info/entry_points.txt
mseep_solscan_mcp_server-0.2.1.dist-info/top_level.txt
mseep_solscan_mcp_server-0.2.1.dist-info/RECORD
